{"version": "1.0", "gameId": "qi-qin-meng-huo", "description": "《七擒孟获》过场动画数据 - 第1关完整过场序列", "cutscenes": [{"id": "cutscene_l1_opening", "levelId": "level_01", "trigger": "level_start", "title": "第一擒 · 开场", "durationSec": 8.0, "skippable": true, "firstPlayLockSec": 2.0, "scenes": [{"type": "screen_fade", "data": {"from": "black", "to": "visible", "duration": 1.5}}, {"type": "camera_move", "data": {"target": "zhuge_position", "duration": 2.0, "easing": "ease_out"}}, {"type": "dialog_show", "data": {"dialogId": "l1_opening_zhuge_01"}}, {"type": "dialog_show", "data": {"dialogId": "l1_opening_zhuge_02"}}, {"type": "camera_move", "data": {"target": "player_spawn", "duration": 1.5, "easing": "ease_in_out"}}, {"type": "screen_tint", "data": {"color": "white", "duration": 0.3, "hold": 0.2}}, {"type": "enable_player_control", "data": {}}], "bgm": {"start": "bgm_level_01_intro", "fadeDuration": 1.0}}, {"id": "cutscene_l1_boss_intro", "levelId": "level_01", "trigger": "boss_arena_enter", "title": "孟获登场", "durationSec": 10.0, "skippable": false, "firstPlayLockSec": 3.0, "scenes": [{"type": "screen_shake", "data": {"intensity": "medium", "duration": 1.0}}, {"type": "camera_zoom", "data": {"target": "zoom_in", "level": 1.3, "duration": 1.5}}, {"type": "boss_appear", "data": {"bossType": "menghuo_elephant", "entryStyle": "charge_from_right"}}, {"type": "effect_particle", "data": {"type": "dust_cloud", "position": "boss_ground", "duration": 1.0}}, {"type": "dialog_show", "data": {"dialogId": "l1_boss_intro_menghuo_01"}}, {"type": "dialog_show", "data": {"dialogId": "l1_boss_intro_menghuo_02"}}, {"type": "camera_zoom", "data": {"target": "reset", "duration": 1.0}}, {"type": "boss_activate_ai", "data": {}}, {"type": "show_boss_hp_bar", "data": {}}], "bgm": {"transitionTo": "bgm_level_01_boss", "fadeDuration": 2.0}}, {"id": "cutscene_l1_capture", "levelId": "level_01", "trigger": "boss_hp_zero", "title": "擒获孟获", "durationSec": 12.0, "skippable": false, "firstPlayLockSec": 4.0, "scenes": [{"type": "disable_player_control", "data": {}}, {"type": "boss_state_change", "data": {"from": "fighting", "to": "defeated"}}, {"type": "camera_focus", "data": {"target": "boss", "duration": 1.0, "zoomLevel": 1.2}}, {"type": "animation_play", "data": {"target": "boss", "anim": "fall_from_elephant", "loop": false}}, {"type": "effect_screen_flash", "data": {"color": "white", "duration": 0.3}}, {"type": "animation_play", "data": {"target": "boss", "anim": "captured_bound", "loop": false}}, {"type": "dialog_show", "data": {"dialogId": "l1_capture_menghuo_01"}}, {"type": "dialog_show", "data": {"dialogId": "l1_capture_menghuo_02"}}, {"type": "effect_particles", "data": {"type": "rope_bindings", "position": "boss", "duration": 2.0}}], "bgm": {"transitionTo": "bgm_cutscene_tense", "fadeDuration": 1.5}}, {"id": "cutscene_l1_release", "levelId": "level_01", "trigger": "capture_scene_complete", "title": "诸葛亮释孟获", "durationSec": 15.0, "skippable": false, "firstPlayLockSec": 5.0, "scenes": [{"type": "camera_move", "data": {"target": "center_stage", "duration": 2.0}}, {"type": "npc_enter", "data": {"npcId": "zhuge_liang", "enterFrom": "left", "walkDuration": 2.0}}, {"type": "npc_face", "data": {"npcId": "zhuge_liang", "faceTarget": "menghuo"}}, {"type": "dialog_show", "data": {"dialogId": "l1_release_zhuge_01"}}, {"type": "animation_play", "data": {"target": "zhuge_liang", "anim": "gesture_peaceful", "loop": false}}, {"type": "dialog_show", "data": {"dialogId": "l1_release_zhuge_02"}}, {"type": "npc_action", "data": {"npcId": "zhuge_liang", "action": "untie_gesture"}}, {"type": "animation_play", "data": {"target": "menghuo", "anim": "released_stand_up", "loop": false}}, {"type": "dialog_show", "data": {"dialogId": "l1_release_menghuo_reaction"}}, {"type": "npc_exit", "data": {"npcId": "menghuo", "exitTo": "right", "walkDuration": 2.5, "expression": "confused_angry"}}, {"type": "dialog_show", "data": {"dialogId": "l1_player_thought_02"}}, {"type": "camera_move", "data": {"target": "player", "duration": 1.5}}, {"type": "enable_player_control", "data": {}}], "bgm": {"transitionTo": "bgm_cutscene_calm", "fadeDuration": 2.0}}, {"id": "cutscene_l1_victory", "levelId": "level_01", "trigger": "release_scene_complete", "title": "第一擒完成", "durationSec": 6.0, "skippable": true, "firstPlayLockSec": 1.0, "scenes": [{"type": "screen_fade", "data": {"from": "visible", "to": "black", "duration": 1.0}}, {"type": "show_result_screen", "data": {"type": "victory", "title": "第一擒完成", "subtitle": "西洱河初战", "stats": ["用时", "击杀数", "受伤次数"]}}, {"type": "check_fragment_unlock", "data": {"fragmentId": "fragment_01_historical_context"}}, {"type": "show_next_level_hint", "data": {"nextLevel": "level_02", "title": "第二擒 · 锦带山夜袭"}}], "bgm": {"play": "bgm_victory_fanfare", "fadeDuration": 1.0}}]}